{
  "live_data": {
    "details": {
      "away_points": 129,
      "home_points": 139,
      "last_event_created_ts": 1773193116,
      "last_event_is_timeout": false,
      "last_play": "End of 4th Quarter.",
      "last_updated_ts": 1773195000,
      "period": 4,
      "period_remaining_time": "00:00",
      "period_type": "quarter",
      "player_stats": {
        "00c958c5-01a7-4668-a3b3-669c22526e03": {
          "assists": 0,
          "blocks": 0,
          "field_goals_attempted": 0,
          "field_goals_made": 0,
          "minutes": 0,
          "points": 0,
          "rebounds": 0,
          "starter": false,
          "steals": 0,
          "three_points_attempted": 0,
          "three_points_made": 0,
          "turnovers": 0
        },
        "0a2e3f0b-0b82-4806-aefc-e0130c226b14": {
          "assists": 1,
          "blocks": 0,
          "field_goals_attempted": 4,
          "field_goals_made": 2,
          "minutes": 28,
          "points": 7,
          "rebounds": 1,
          "starter": false,
          "steals": 0,
          "three_points_attempted": 1,
          "three_points_made": 0,
          "turnovers": 0
        },
        "0d3d5fe3-274a-4fd2-a802-ca5429effc95": {
          "assists": 10,
          "blocks": 2,
          "field_goals_attempted": 10,
          "field_goals_made": 9,
          "minutes": 31,
          "points": 32,
          "rebounds": 3,
          "starter": false,
          "steals": 3,
          "three_points_attempted": 8,
          "three_points_made": 8,
          "turnovers": 0
        },
        "155ff771-bdf4-4a16-9908-6b555ff73ace": {
          "assists": 0,
          "blocks": 0,
          "field_goals_attempted": 0,
          "field_goals_made": 0,
          "minutes": 0,
          "points": 0,
          "rebounds": 0,
          "starter": false,
          "steals": 0,
          "three_points_attempted": 0,
          "three_points_made": 0,
          "turnovers": 0
        },
        "1774828d-9afb-4643-81a8-af05aafa6866": {
          "assists": 2,
          "blocks": 0,
          "field_goals_attempted": 16,
          "field_goals_made": 6,
          "minutes": 36,
          "points": 23,
          "rebounds": 3,
          "starter": true,
          "steals": 2,
          "three_points_attempted": 4,
          "three_points_made": 0,
          "turnovers": 2
        },
        "21e37a74-41d2-4c09-9f05-9b20a14ba88b": {
          "assists": 5,
          "blocks": 0,
          "field_goals_attempted": 15,
          "field_goals_made": 7,
          "minutes": 35,
          "points": 21,
          "rebounds": 5,
          "starter": true,
          "steals": 3,
          "three_points_attempted": 5,
          "three_points_made": 1,
          "turnovers": 2
        },
        "3783ab8b-6b24-48d3-835e-3d18b2ebd848": {
          "assists": 2,
          "blocks": 1,
          "field_goals_attempted": 8,
          "field_goals_made": 3,
          "minutes": 26,
          "points": 8,
          "rebounds": 5,
          "starter": true,
          "steals": 0,
          "three_points_attempted": 5,
          "three_points_made": 1,
          "turnovers": 0
        },
        "3956631b-53dc-4cd9-8521-c8a113c806fa": {
          "assists": 0,
          "blocks": 0,
          "field_goals_attempted": 0,
          "field_goals_made": 0,
          "minutes": 0,
          "points": 0,
          "rebounds": 0,
          "starter": false,
          "steals": 0,
          "three_points_attempted": 0,
          "three_points_made": 0,
          "turnovers": 0
        },
        "3a43b825-6a96-4713-bebe-cb83d6583d39": {
          "assists": 1,
          "blocks": 0,
          "field_goals_attempted": 7,
          "field_goals_made": 4,
          "minutes": 34,
          "points": 11,
          "rebounds": 6,
          "starter": true,
          "steals": 0,
          "three_points_attempted": 2,
          "three_points_made": 0,
          "turnovers": 1
        },
        "40a4cc2c-91d4-45c2-9324-d2a527c010f6": {
          "assists": 2,
          "blocks": 2,
          "field_goals_attempted": 5,
          "field_goals_made": 4,
          "minutes": 16,
          "points": 11,
          "rebounds": 4,
          "starter": false,
          "steals": 0,
          "three_points_attempted": 0,
          "three_points_made": 0,
          "turnovers": 2
        },
        "41f8ada0-5160-4cff-b69e-a335d1a9eec7": {
          "assists": 0,
          "blocks": 1,
          "field_goals_attempted": 6,
          "field_goals_made": 4,
          "minutes": 21,
          "points": 11,
          "rebounds": 6,
          "starter": true,
          "steals": 2,
          "three_points_attempted": 1,
          "three_points_made": 1,
          "turnovers": 2
        },
        "43edc187-1d56-40bc-ba15-a7b200a08e8f": {
          "assists": 0,
          "blocks": 0,
          "field_goals_attempted": 3,
          "field_goals_made": 1,
          "minutes": 10,
          "points": 2,
          "rebounds": 2,
          "starter": false,
          "steals": 1,
          "three_points_attempted": 1,
          "three_points_made": 0,
          "turnovers": 0
        },
        "456d20cd-0fd9-46cd-9aec-b56181bccea6": {
          "assists": 0,
          "blocks": 0,
          "field_goals_attempted": 0,
          "field_goals_made": 0,
          "minutes": 0,
          "points": 0,
          "rebounds": 0,
          "starter": false,
          "steals": 0,
          "three_points_attempted": 0,
          "three_points_made": 0,
          "turnovers": 0
        },
        "49771603-2a9e-4029-b716-a0f32150dc14": {
          "assists": 8,
          "blocks": 0,
          "field_goals_attempted": 20,
          "field_goals_made": 10,
          "minutes": 25,
          "points": 26,
          "rebounds": 2,
          "starter": true,
          "steals": 0,
          "three_points_attempted": 10,
          "three_points_made": 4,
          "turnovers": 4
        },
        "4e4462ee-8564-4052-ba81-7c1e416c3e6f": {
          "assists": 0,
          "blocks": 0,
          "field_goals_attempted": 0,
          "field_goals_made": 0,
          "minutes": 0,
          "points": 0,
          "rebounds": 0,
          "starter": false,
          "steals": 0,
          "three_points_attempted": 0,
          "three_points_made": 0,
          "turnovers": 0
        },
        "5b48c281-6f74-4ed0-9252-17fcd483d5c9": {
          "assists": 3,
          "blocks": 0,
          "field_goals_attempted": 8,
          "field_goals_made": 4,
          "minutes": 24,
          "points": 12,
          "rebounds": 1,
          "starter": false,
          "steals": 0,
          "three_points_attempted": 4,
          "three_points_made": 2,
          "turnovers": 1
        },
        "5e85252f-a995-4dc2-8d1e-e7fd7503c803": {
          "assists": 7,
          "blocks": 0,
          "field_goals_attempted": 11,
          "field_goals_made": 5,
          "minutes": 26,
          "points": 12,
          "rebounds": 5,
          "starter": false,
          "steals": 1,
          "three_points_attempted": 3,
          "three_points_made": 1,
          "turnovers": 3
        },
        "605cfa20-dc8e-4c44-90bd-1ee476ec4138": {
          "assists": 1,
          "blocks": 1,
          "field_goals_attempted": 24,
          "field_goals_made": 10,
          "minutes": 38,
          "points": 30,
          "rebounds": 12,
          "starter": true,
          "steals": 2,
          "three_points_attempted": 9,
          "three_points_made": 1,
          "turnovers": 3
        },
        "6f210c61-f8c9-4fb0-84d0-d597c102bca4": {
          "assists": 0,
          "blocks": 0,
          "field_goals_attempted": 0,
          "field_goals_made": 0,
          "minutes": 0,
          "points": 0,
          "rebounds": 0,
          "starter": false,
          "steals": 0,
          "three_points_attempted": 0,
          "three_points_made": 0,
          "turnovers": 0
        },
        "751fd761-96ac-4859-aade-a38d1e2d5c4c": {
          "assists": 0,
          "blocks": 0,
          "field_goals_attempted": 0,
          "field_goals_made": 0,
          "minutes": 0,
          "points": 0,
          "rebounds": 0,
          "starter": false,
          "steals": 0,
          "three_points_attempted": 0,
          "three_points_made": 0,
          "turnovers": 0
        },
        "7ae937e9-691a-4645-9e65-29e0f5713858": {
          "assists": 0,
          "blocks": 0,
          "field_goals_attempted": 11,
          "field_goals_made": 4,
          "minutes": 22,
          "points": 11,
          "rebounds": 3,
          "starter": true,
          "steals": 0,
          "three_points_attempted": 9,
          "three_points_made": 3,
          "turnovers": 0
        },
        "8aa20fec-25b0-47c8-bd26-efd64ee0826c": {
          "assists": 0,
          "blocks": 0,
          "field_goals_attempted": 0,
          "field_goals_made": 0,
          "minutes": 0,
          "points": 0,
          "rebounds": 0,
          "starter": false,
          "steals": 0,
          "three_points_attempted": 0,
          "three_points_made": 0,
          "turnovers": 0
        },
        "8bcb0399-a016-42af-bbc8-b701f99abb96": {
          "assists": 0,
          "blocks": 0,
          "field_goals_attempted": 0,
          "field_goals_made": 0,
          "minutes": 0,
          "points": 0,
          "rebounds": 0,
          "starter": false,
          "steals": 0,
          "three_points_attempted": 0,
          "three_points_made": 0,
          "turnovers": 0
        },
        "90456e7e-47d2-483c-afe5-b6bacec17b2f": {
          "assists": 0,
          "blocks": 0,
          "field_goals_attempted": 0,
          "field_goals_made": 0,
          "minutes": 0,
          "points": 0,
          "rebounds": 0,
          "starter": false,
          "steals": 0,
          "three_points_attempted": 0,
          "three_points_made": 0,
          "turnovers": 0
        },
        "9b1d114b-c1a7-455b-bb66-f6b74d7bec51": {
          "assists": 0,
          "blocks": 0,
          "field_goals_attempted": 9,
          "field_goals_made": 6,
          "minutes": 23,
          "points": 14,
          "rebounds": 2,
          "starter": false,
          "steals": 1,
          "three_points_attempted": 3,
          "three_points_made": 2,
          "turnovers": 0
        },
        "9b80ae56-086e-42ad-9d22-f4e5af386852": {
          "assists": 1,
          "blocks": 0,
          "field_goals_attempted": 0,
          "field_goals_made": 0,
          "minutes": 7,
          "points": 0,
          "rebounds": 0,
          "starter": false,
          "steals": 1,
          "three_points_attempted": 0,
          "three_points_made": 0,
          "turnovers": 0
        },
        "bcd4c0ae-6e30-47ea-a549-eb7f70b8147a": {
          "assists": 0,
          "blocks": 0,
          "field_goals_attempted": 0,
          "field_goals_made": 0,
          "minutes": 0,
          "points": 0,
          "rebounds": 0,
          "starter": false,
          "steals": 0,
          "three_points_attempted": 0,
          "three_points_made": 0,
          "turnovers": 0
        },
        "bea22e75-78de-4403-98b8-953d4a69aed4": {
          "assists": 0,
          "blocks": 0,
          "field_goals_attempted": 0,
          "field_goals_made": 0,
          "minutes": 0,
          "points": 0,
          "rebounds": 0,
          "starter": false,
          "steals": 0,
          "three_points_attempted": 0,
          "three_points_made": 0,
          "turnovers": 0
        },
        "c2755450-76a7-4d77-a5cc-de4e980c0f92": {
          "assists": 0,
          "blocks": 0,
          "field_goals_attempted": 0,
          "field_goals_made": 0,
          "minutes": 0,
          "points": 0,
          "rebounds": 0,
          "starter": false,
          "steals": 0,
          "three_points_attempted": 0,
          "three_points_made": 0,
          "turnovers": 0
        },
        "d4740e21-0c79-4424-a03e-0b17e213a846": {
          "assists": 4,
          "blocks": 0,
          "field_goals_attempted": 3,
          "field_goals_made": 2,
          "minutes": 22,
          "points": 5,
          "rebounds": 2,
          "starter": false,
          "steals": 0,
          "three_points_attempted": 2,
          "three_points_made": 1,
          "turnovers": 0
        },
        "d6d1d5a3-80ef-4687-af8c-dfaae4d6ea92": {
          "assists": 0,
          "blocks": 0,
          "field_goals_attempted": 0,
          "field_goals_made": 0,
          "minutes": 0,
          "points": 0,
          "rebounds": 0,
          "starter": false,
          "steals": 0,
          "three_points_attempted": 0,
          "three_points_made": 0,
          "turnovers": 0
        },
        "dea3d9c3-c6fd-4f7a-bb80-ac4ae029c114": {
          "assists": 0,
          "blocks": 0,
          "field_goals_attempted": 0,
          "field_goals_made": 0,
          "minutes": 0,
          "points": 0,
          "rebounds": 0,
          "starter": false,
          "steals": 0,
          "three_points_attempted": 0,
          "three_points_made": 0,
          "turnovers": 0
        },
        "f438ad3e-c75f-45b5-af2a-bf90dbf16fdd": {
          "assists": 2,
          "blocks": 0,
          "field_goals_attempted": 12,
          "field_goals_made": 6,
          "minutes": 25,
          "points": 15,
          "rebounds": 3,
          "starter": false,
          "steals": 0,
          "three_points_attempted": 4,
          "three_points_made": 1,
          "turnovers": 6
        },
        "f51d60f4-2633-4be8-b49c-d09a42c6051c": {
          "assists": 1,
          "blocks": 0,
          "field_goals_attempted": 3,
          "field_goals_made": 2,
          "minutes": 16,
          "points": 4,
          "rebounds": 3,
          "starter": true,
          "steals": 1,
          "three_points_attempted": 0,
          "three_points_made": 0,
          "turnovers": 0
        },
        "fc56c21a-a5a1-4ac3-aa90-1eb74d41da9f": {
          "assists": 3,
          "blocks": 1,
          "field_goals_attempted": 8,
          "field_goals_made": 4,
          "minutes": 24,
          "points": 13,
          "rebounds": 16,
          "starter": true,
          "steals": 1,
          "three_points_attempted": 3,
          "three_points_made": 2,
          "turnovers": 4
        },
        "fe5a04a5-0dc7-4373-baf9-36c4bced83a5": {
          "assists": 0,
          "blocks": 0,
          "field_goals_attempted": 0,
          "field_goals_made": 0,
          "minutes": 0,
          "points": 0,
          "rebounds": 0,
          "starter": false,
          "steals": 0,
          "three_points_attempted": 0,
          "three_points_made": 0,
          "turnovers": 0
        }
      },
      "possession": "",
      "score_last_updated_ts": 1773193092,
      "series_stats": {
        "KXNBA3PT": "three_points_made",
        "KXNBAAST": "assists",
        "KXNBABLK": "blocks",
        "KXNBAPTS": "points",
        "KXNBAREB": "rebounds",
        "KXNBASTL": "steals"
      },
      "status": "closed",
      "widget_status": "finished",
      "winner": "583ec87d-fb46-11e1-82cb-f4ce4684ea4c"
    },
    "milestone_id": "a12a2915-66bb-45db-b92e-09e3cb5277cc",
    "type": "basketball_game"
  }
}
