{
  "live_data": {
    "details": {
      "away_points": 108,
      "home_points": 119,
      "last_event_created_ts": 1773463815,
      "last_event_is_timeout": false,
      "last_play": "End of 4th Quarter.",
      "last_updated_ts": 1773464732,
      "period": 4,
      "period_remaining_time": "00:00",
      "period_type": "quarter",
      "player_stats": {
        "089f34c8-a9fa-480b-9b91-aa417097d552": {
          "assists": 0,
          "blocks": 0,
          "field_goals_attempted": 0,
          "field_goals_made": 0,
          "minutes": 0,
          "points": 0,
          "rebounds": 0,
          "starter": false,
          "steals": 0,
          "three_points_attempted": 0,
          "three_points_made": 0,
          "turnovers": 0
        },
        "0be3d8cd-ec75-442f-9b05-b6acaac19315": {
          "assists": 2,
          "blocks": 5,
          "field_goals_attempted": 10,
          "field_goals_made": 5,
          "minutes": 32,
          "points": 11,
          "rebounds": 7,
          "starter": true,
          "steals": 0,
          "three_points_attempted": 4,
          "three_points_made": 1,
          "turnovers": 0
        },
        "0faf4911-89b0-49ae-a920-0912c6e6a92e": {
          "assists": 2,
          "blocks": 0,
          "field_goals_attempted": 11,
          "field_goals_made": 10,
          "minutes": 30,
          "points": 21,
          "rebounds": 1,
          "starter": true,
          "steals": 0,
          "three_points_attempted": 0,
          "three_points_made": 0,
          "turnovers": 2
        },
        "11ac6d0a-2082-45a8-a091-71c8950eab5f": {
          "assists": 4,
          "blocks": 1,
          "field_goals_attempted": 3,
          "field_goals_made": 1,
          "minutes": 17,
          "points": 3,
          "rebounds": 3,
          "starter": false,
          "steals": 0,
          "three_points_attempted": 3,
          "three_points_made": 1,
          "turnovers": 0
        },
        "2a5b8fd6-50da-499a-a50b-832f02dea356": {
          "assists": 0,
          "blocks": 0,
          "field_goals_attempted": 0,
          "field_goals_made": 0,
          "minutes": 0,
          "points": 0,
          "rebounds": 0,
          "starter": false,
          "steals": 0,
          "three_points_attempted": 0,
          "three_points_made": 0,
          "turnovers": 0
        },
        "37104adf-2343-40fe-8d8a-a11f89d037e8": {
          "assists": 0,
          "blocks": 0,
          "field_goals_attempted": 0,
          "field_goals_made": 0,
          "minutes": 0,
          "points": 0,
          "rebounds": 0,
          "starter": false,
          "steals": 0,
          "three_points_attempted": 0,
          "three_points_made": 0,
          "turnovers": 0
        },
        "39063bb2-a56e-41bb-94ca-ae15c380a190": {
          "assists": 4,
          "blocks": 0,
          "field_goals_attempted": 9,
          "field_goals_made": 5,
          "minutes": 25,
          "points": 12,
          "rebounds": 4,
          "starter": false,
          "steals": 1,
          "three_points_attempted": 3,
          "three_points_made": 2,
          "turnovers": 3
        },
        "3e76dbce-174a-45f6-8019-5c1f483aadbe": {
          "assists": 0,
          "blocks": 0,
          "field_goals_attempted": 0,
          "field_goals_made": 0,
          "minutes": 0,
          "points": 0,
          "rebounds": 0,
          "starter": false,
          "steals": 0,
          "three_points_attempted": 0,
          "three_points_made": 0,
          "turnovers": 0
        },
        "4624140d-4700-4bc6-a78b-79acc60ce3fe": {
          "assists": 1,
          "blocks": 3,
          "field_goals_attempted": 10,
          "field_goals_made": 3,
          "minutes": 30,
          "points": 10,
          "rebounds": 8,
          "starter": true,
          "steals": 0,
          "three_points_attempted": 3,
          "three_points_made": 1,
          "turnovers": 1
        },
        "4bf6560d-e40d-4412-b8c4-de4de06b42ac": {
          "assists": 0,
          "blocks": 0,
          "field_goals_attempted": 0,
          "field_goals_made": 0,
          "minutes": 0,
          "points": 0,
          "rebounds": 0,
          "starter": false,
          "steals": 0,
          "three_points_attempted": 0,
          "three_points_made": 0,
          "turnovers": 0
        },
        "5cef9632-cd85-406e-8441-661e2cc1657c": {
          "assists": 0,
          "blocks": 0,
          "field_goals_attempted": 0,
          "field_goals_made": 0,
          "minutes": 0,
          "points": 0,
          "rebounds": 0,
          "starter": false,
          "steals": 0,
          "three_points_attempted": 0,
          "three_points_made": 0,
          "turnovers": 0
        },
        "5fe0b2a4-3e64-4451-a42d-bec734ea1199": {
          "assists": 3,
          "blocks": 0,
          "field_goals_attempted": 8,
          "field_goals_made": 4,
          "minutes": 26,
          "points": 11,
          "rebounds": 6,
          "starter": true,
          "steals": 1,
          "three_points_attempted": 7,
          "three_points_made": 3,
          "turnovers": 1
        },
        "614ded35-dec0-4703-aaad-1abb645ad47b": {
          "assists": 6,
          "blocks": 0,
          "field_goals_attempted": 11,
          "field_goals_made": 4,
          "minutes": 29,
          "points": 8,
          "rebounds": 4,
          "starter": true,
          "steals": 2,
          "three_points_attempted": 4,
          "three_points_made": 0,
          "turnovers": 0
        },
        "7c4044ea-fb72-430d-b08b-19bfe77bf24d": {
          "assists": 0,
          "blocks": 0,
          "field_goals_attempted": 0,
          "field_goals_made": 0,
          "minutes": 0,
          "points": 0,
          "rebounds": 0,
          "starter": false,
          "steals": 0,
          "three_points_attempted": 0,
          "three_points_made": 0,
          "turnovers": 0
        },
        "94894b15-fc9f-42e5-854c-4d2a6006c09b": {
          "assists": 0,
          "blocks": 0,
          "field_goals_attempted": 0,
          "field_goals_made": 0,
          "minutes": 0,
          "points": 0,
          "rebounds": 0,
          "starter": false,
          "steals": 0,
          "three_points_attempted": 0,
          "three_points_made": 0,
          "turnovers": 0
        },
        "94cad9c3-833e-410a-a028-6cd25fdb20d9": {
          "assists": 0,
          "blocks": 0,
          "field_goals_attempted": 0,
          "field_goals_made": 0,
          "minutes": 0,
          "points": 0,
          "rebounds": 0,
          "starter": false,
          "steals": 0,
          "three_points_attempted": 0,
          "three_points_made": 0,
          "turnovers": 0
        },
        "98a42c36-71d9-400e-95a5-e7fe53f7e9d8": {
          "assists": 0,
          "blocks": 0,
          "field_goals_attempted": 0,
          "field_goals_made": 0,
          "minutes": 1,
          "points": 0,
          "rebounds": 0,
          "starter": false,
          "steals": 0,
          "three_points_attempted": 0,
          "three_points_made": 0,
          "turnovers": 0
        },
        "998569d5-8e34-4b4b-a396-aada418a9fc1": {
          "assists": 0,
          "blocks": 0,
          "field_goals_attempted": 0,
          "field_goals_made": 0,
          "minutes": 0,
          "points": 0,
          "rebounds": 0,
          "starter": false,
          "steals": 0,
          "three_points_attempted": 0,
          "three_points_made": 0,
          "turnovers": 0
        },
        "a0efcc22-65e6-45a1-a474-6df949cd1613": {
          "assists": 3,
          "blocks": 3,
          "field_goals_attempted": 5,
          "field_goals_made": 4,
          "minutes": 34,
          "points": 10,
          "rebounds": 6,
          "starter": true,
          "steals": 2,
          "three_points_attempted": 2,
          "three_points_made": 1,
          "turnovers": 0
        },
        "a21967f6-3de2-4e6e-ad5c-b011117e05a6": {
          "assists": 0,
          "blocks": 0,
          "field_goals_attempted": 0,
          "field_goals_made": 0,
          "minutes": 4,
          "points": 0,
          "rebounds": 0,
          "starter": false,
          "steals": 0,
          "three_points_attempted": 0,
          "three_points_made": 0,
          "turnovers": 0
        },
        "a4baed3c-0021-407e-8448-a298594c2a83": {
          "assists": 10,
          "blocks": 1,
          "field_goals_attempted": 20,
          "field_goals_made": 8,
          "minutes": 39,
          "points": 20,
          "rebounds": 11,
          "starter": true,
          "steals": 2,
          "three_points_attempted": 11,
          "three_points_made": 4,
          "turnovers": 2
        },
        "a92fc5be-ca62-4f8c-b4dc-bd7b15cf755b": {
          "assists": 1,
          "blocks": 3,
          "field_goals_attempted": 7,
          "field_goals_made": 0,
          "minutes": 23,
          "points": 2,
          "rebounds": 3,
          "starter": false,
          "steals": 0,
          "three_points_attempted": 6,
          "three_points_made": 0,
          "turnovers": 2
        },
        "abceeb28-05cc-48d9-bb9a-bd421c30dfe8": {
          "assists": 2,
          "blocks": 0,
          "field_goals_attempted": 18,
          "field_goals_made": 6,
          "minutes": 35,
          "points": 18,
          "rebounds": 11,
          "starter": true,
          "steals": 0,
          "three_points_attempted": 10,
          "three_points_made": 2,
          "turnovers": 2
        },
        "b20be183-d7e6-4970-ad6f-04ff489eb0d9": {
          "assists": 3,
          "blocks": 0,
          "field_goals_attempted": 14,
          "field_goals_made": 6,
          "minutes": 36,
          "points": 14,
          "rebounds": 8,
          "starter": true,
          "steals": 2,
          "three_points_attempted": 5,
          "three_points_made": 0,
          "turnovers": 0
        },
        "b800a5e4-18bc-4402-b69e-402167501632": {
          "assists": 0,
          "blocks": 0,
          "field_goals_attempted": 0,
          "field_goals_made": 0,
          "minutes": 0,
          "points": 0,
          "rebounds": 0,
          "starter": false,
          "steals": 0,
          "three_points_attempted": 0,
          "three_points_made": 0,
          "turnovers": 0
        },
        "bc23524b-03f6-49eb-8fb0-a365aa39bfb7": {
          "assists": 0,
          "blocks": 0,
          "field_goals_attempted": 0,
          "field_goals_made": 0,
          "minutes": 0,
          "points": 0,
          "rebounds": 0,
          "starter": false,
          "steals": 0,
          "three_points_attempted": 0,
          "three_points_made": 0,
          "turnovers": 0
        },
        "beada20d-6def-48b5-8cdf-ca243e06640d": {
          "assists": 0,
          "blocks": 0,
          "field_goals_attempted": 0,
          "field_goals_made": 0,
          "minutes": 0,
          "points": 0,
          "rebounds": 0,
          "starter": false,
          "steals": 0,
          "three_points_attempted": 0,
          "three_points_made": 0,
          "turnovers": 0
        },
        "c8b85545-69a3-45eb-b054-fac03220e0d1": {
          "assists": 3,
          "blocks": 1,
          "field_goals_attempted": 13,
          "field_goals_made": 6,
          "minutes": 27,
          "points": 14,
          "rebounds": 3,
          "starter": false,
          "steals": 1,
          "three_points_attempted": 1,
          "three_points_made": 0,
          "turnovers": 1
        },
        "d0717f7b-1a4f-4a69-9bd8-14eac244be0c": {
          "assists": 0,
          "blocks": 0,
          "field_goals_attempted": 0,
          "field_goals_made": 0,
          "minutes": 0,
          "points": 0,
          "rebounds": 0,
          "starter": false,
          "steals": 0,
          "three_points_attempted": 0,
          "three_points_made": 0,
          "turnovers": 0
        },
        "e1936136-417a-4892-b6e0-90e41b6c2f1a": {
          "assists": 0,
          "blocks": 0,
          "field_goals_attempted": 6,
          "field_goals_made": 4,
          "minutes": 20,
          "points": 11,
          "rebounds": 2,
          "starter": false,
          "steals": 0,
          "three_points_attempted": 3,
          "three_points_made": 3,
          "turnovers": 1
        },
        "ea5c84e5-a9cf-48d2-8057-e57ce9ea2387": {
          "assists": 0,
          "blocks": 0,
          "field_goals_attempted": 0,
          "field_goals_made": 0,
          "minutes": 0,
          "points": 0,
          "rebounds": 0,
          "starter": false,
          "steals": 0,
          "three_points_attempted": 0,
          "three_points_made": 0,
          "turnovers": 0
        },
        "ef369e50-d57e-499e-8219-841ac142f166": {
          "assists": 0,
          "blocks": 0,
          "field_goals_attempted": 0,
          "field_goals_made": 0,
          "minutes": 0,
          "points": 0,
          "rebounds": 0,
          "starter": false,
          "steals": 0,
          "three_points_attempted": 0,
          "three_points_made": 0,
          "turnovers": 0
        },
        "f2bfdc6c-0d84-4736-ba44-8cdbc196e0b3": {
          "assists": 3,
          "blocks": 0,
          "field_goals_attempted": 22,
          "field_goals_made": 8,
          "minutes": 34,
          "points": 28,
          "rebounds": 4,
          "starter": true,
          "steals": 1,
          "three_points_attempted": 6,
          "three_points_made": 2,
          "turnovers": 2
        },
        "f7e7a36e-601e-4130-a819-fa9f752bd14a": {
          "assists": 2,
          "blocks": 2,
          "field_goals_attempted": 5,
          "field_goals_made": 4,
          "minutes": 17,
          "points": 8,
          "rebounds": 7,
          "starter": false,
          "steals": 0,
          "three_points_attempted": 0,
          "three_points_made": 0,
          "turnovers": 0
        },
        "f8f0ddf3-54aa-4c03-97c8-233022cc5d3a": {
          "assists": 0,
          "blocks": 0,
          "field_goals_attempted": 0,
          "field_goals_made": 0,
          "minutes": 0,
          "points": 0,
          "rebounds": 0,
          "starter": false,
          "steals": 0,
          "three_points_attempted": 0,
          "three_points_made": 0,
          "turnovers": 0
        },
        "f9912228-d55a-404f-b2e5-824658b21dc4": {
          "assists": 2,
          "blocks": 0,
          "field_goals_attempted": 19,
          "field_goals_made": 10,
          "minutes": 28,
          "points": 26,
          "rebounds": 6,
          "starter": false,
          "steals": 1,
          "three_points_attempted": 5,
          "three_points_made": 1,
          "turnovers": 2
        }
      },
      "possession": "",
      "score_last_updated_ts": 1773463785,
      "series_stats": {
        "KXNBA3PT": "three_points_made",
        "KXNBAAST": "assists",
        "KXNBABLK": "blocks",
        "KXNBAPTS": "points",
        "KXNBAREB": "rebounds",
        "KXNBASTL": "steals"
      },
      "status": "closed",
      "widget_status": "finished",
      "winner": "583ecdfb-fb46-11e1-82cb-f4ce4684ea4c"
    },
    "milestone_id": "d50a169b-6063-41e7-bd95-b2440f2e6c40",
    "type": "basketball_game"
  }
}
