{
  "live_data": {
    "details": {
      "away_points": 107,
      "home_points": 115,
      "last_event_created_ts": 1772767781,
      "last_event_is_timeout": false,
      "last_play": "End of 4th Quarter.",
      "last_updated_ts": 1772768722,
      "period": 4,
      "period_remaining_time": "00:00",
      "period_type": "quarter",
      "player_stats": {
        "0f3fa1bc-e62a-4ea6-b30e-8f77f6f625f8": {
          "assists": 0,
          "blocks": 0,
          "field_goals_attempted": 0,
          "field_goals_made": 0,
          "minutes": 0,
          "points": 0,
          "rebounds": 0,
          "starter": false,
          "steals": 0,
          "three_points_attempted": 0,
          "three_points_made": 0,
          "turnovers": 0
        },
        "14647265-8f75-4624-abab-5b6f9d1ef5cb": {
          "assists": 0,
          "blocks": 0,
          "field_goals_attempted": 1,
          "field_goals_made": 1,
          "minutes": 4,
          "points": 2,
          "rebounds": 0,
          "starter": false,
          "steals": 0,
          "three_points_attempted": 0,
          "three_points_made": 0,
          "turnovers": 0
        },
        "14713689-92a3-4b09-b657-e49d2cbc31f0": {
          "assists": 1,
          "blocks": 1,
          "field_goals_attempted": 8,
          "field_goals_made": 5,
          "minutes": 24,
          "points": 11,
          "rebounds": 2,
          "starter": false,
          "steals": 1,
          "three_points_attempted": 2,
          "three_points_made": 1,
          "turnovers": 1
        },
        "15a36614-d0eb-4be8-af9f-4e79a32d4231": {
          "assists": 1,
          "blocks": 1,
          "field_goals_attempted": 12,
          "field_goals_made": 5,
          "minutes": 21,
          "points": 12,
          "rebounds": 6,
          "starter": false,
          "steals": 0,
          "three_points_attempted": 5,
          "three_points_made": 1,
          "turnovers": 1
        },
        "19e432c3-e255-428c-94d0-cedebed3dfc5": {
          "assists": 2,
          "blocks": 0,
          "field_goals_attempted": 7,
          "field_goals_made": 4,
          "minutes": 27,
          "points": 16,
          "rebounds": 5,
          "starter": true,
          "steals": 2,
          "three_points_attempted": 6,
          "three_points_made": 4,
          "turnovers": 1
        },
        "1ac8b21f-fa4e-4bd5-938c-02471a8ead10": {
          "assists": 0,
          "blocks": 0,
          "field_goals_attempted": 0,
          "field_goals_made": 0,
          "minutes": 0,
          "points": 0,
          "rebounds": 0,
          "starter": false,
          "steals": 0,
          "three_points_attempted": 0,
          "three_points_made": 0,
          "turnovers": 0
        },
        "1cefe214-8a3b-42d1-a667-4e30137e88b9": {
          "assists": 0,
          "blocks": 0,
          "field_goals_attempted": 2,
          "field_goals_made": 1,
          "minutes": 4,
          "points": 2,
          "rebounds": 4,
          "starter": false,
          "steals": 0,
          "three_points_attempted": 0,
          "three_points_made": 0,
          "turnovers": 0
        },
        "2bf5e35d-4c07-42ff-bcc0-e2e7b05eab71": {
          "assists": 4,
          "blocks": 0,
          "field_goals_attempted": 11,
          "field_goals_made": 5,
          "minutes": 34,
          "points": 17,
          "rebounds": 8,
          "starter": true,
          "steals": 1,
          "three_points_attempted": 2,
          "three_points_made": 0,
          "turnovers": 2
        },
        "2f1946d8-9bb5-472b-803a-206835b7b87e": {
          "assists": 4,
          "blocks": 0,
          "field_goals_attempted": 4,
          "field_goals_made": 2,
          "minutes": 16,
          "points": 4,
          "rebounds": 3,
          "starter": false,
          "steals": 0,
          "three_points_attempted": 0,
          "three_points_made": 0,
          "turnovers": 0
        },
        "36ea9bc5-23b0-4274-9c6c-cd8a07b1b654": {
          "assists": 3,
          "blocks": 0,
          "field_goals_attempted": 12,
          "field_goals_made": 8,
          "minutes": 35,
          "points": 22,
          "rebounds": 4,
          "starter": true,
          "steals": 1,
          "three_points_attempted": 8,
          "three_points_made": 5,
          "turnovers": 4
        },
        "37610450-b248-4427-b2d0-ff7fe6973eab": {
          "assists": 0,
          "blocks": 0,
          "field_goals_attempted": 0,
          "field_goals_made": 0,
          "minutes": 0,
          "points": 0,
          "rebounds": 0,
          "starter": false,
          "steals": 0,
          "three_points_attempted": 0,
          "three_points_made": 0,
          "turnovers": 0
        },
        "4432f713-dfc6-47db-881d-bace88c4d9c1": {
          "assists": 4,
          "blocks": 0,
          "field_goals_attempted": 6,
          "field_goals_made": 3,
          "minutes": 22,
          "points": 8,
          "rebounds": 2,
          "starter": true,
          "steals": 1,
          "three_points_attempted": 3,
          "three_points_made": 1,
          "turnovers": 2
        },
        "4d76b816-4ca3-4a92-bbd3-489819b6821b": {
          "assists": 0,
          "blocks": 0,
          "field_goals_attempted": 0,
          "field_goals_made": 0,
          "minutes": 0,
          "points": 0,
          "rebounds": 0,
          "starter": false,
          "steals": 0,
          "three_points_attempted": 0,
          "three_points_made": 0,
          "turnovers": 0
        },
        "56f10c2a-0978-4e58-a434-01d46c704482": {
          "assists": 0,
          "blocks": 0,
          "field_goals_attempted": 0,
          "field_goals_made": 0,
          "minutes": 0,
          "points": 0,
          "rebounds": 0,
          "starter": false,
          "steals": 0,
          "three_points_attempted": 0,
          "three_points_made": 0,
          "turnovers": 0
        },
        "726401ab-6c3f-4f7e-be74-5c71921d2d4c": {
          "assists": 0,
          "blocks": 0,
          "field_goals_attempted": 0,
          "field_goals_made": 0,
          "minutes": 0,
          "points": 0,
          "rebounds": 0,
          "starter": false,
          "steals": 0,
          "three_points_attempted": 0,
          "three_points_made": 0,
          "turnovers": 0
        },
        "7b22d659-5c24-411c-937b-23352fdefff6": {
          "assists": 0,
          "blocks": 0,
          "field_goals_attempted": 1,
          "field_goals_made": 0,
          "minutes": 4,
          "points": 0,
          "rebounds": 0,
          "starter": false,
          "steals": 1,
          "three_points_attempted": 0,
          "three_points_made": 0,
          "turnovers": 0
        },
        "81b37b7d-b0ec-4d2f-a97b-505763a51fd0": {
          "assists": 7,
          "blocks": 0,
          "field_goals_attempted": 10,
          "field_goals_made": 6,
          "minutes": 31,
          "points": 18,
          "rebounds": 3,
          "starter": true,
          "steals": 1,
          "three_points_attempted": 4,
          "three_points_made": 2,
          "turnovers": 2
        },
        "85df4482-17a9-49b8-b40f-b6cddb54e579": {
          "assists": 0,
          "blocks": 0,
          "field_goals_attempted": 0,
          "field_goals_made": 0,
          "minutes": 0,
          "points": 0,
          "rebounds": 0,
          "starter": false,
          "steals": 0,
          "three_points_attempted": 0,
          "three_points_made": 0,
          "turnovers": 0
        },
        "930f19e3-6885-4738-9dae-484cb321f64f": {
          "assists": 1,
          "blocks": 1,
          "field_goals_attempted": 11,
          "field_goals_made": 6,
          "minutes": 28,
          "points": 13,
          "rebounds": 1,
          "starter": false,
          "steals": 3,
          "three_points_attempted": 2,
          "three_points_made": 1,
          "turnovers": 0
        },
        "95551002-8e7e-4af7-b21e-71c4efe0573e": {
          "assists": 2,
          "blocks": 0,
          "field_goals_attempted": 16,
          "field_goals_made": 5,
          "minutes": 30,
          "points": 14,
          "rebounds": 5,
          "starter": true,
          "steals": 1,
          "three_points_attempted": 1,
          "three_points_made": 0,
          "turnovers": 1
        },
        "994b09f9-3e74-44d3-8d9b-1a9347c3c92f": {
          "assists": 2,
          "blocks": 1,
          "field_goals_attempted": 0,
          "field_goals_made": 0,
          "minutes": 10,
          "points": 0,
          "rebounds": 1,
          "starter": false,
          "steals": 0,
          "three_points_attempted": 0,
          "three_points_made": 0,
          "turnovers": 2
        },
        "9c875ec2-a062-4b15-9621-d5786b40a985": {
          "assists": 0,
          "blocks": 0,
          "field_goals_attempted": 1,
          "field_goals_made": 0,
          "minutes": 4,
          "points": 0,
          "rebounds": 0,
          "starter": false,
          "steals": 0,
          "three_points_attempted": 0,
          "three_points_made": 0,
          "turnovers": 0
        },
        "9d88c781-8100-4e55-be27-a39b97105be4": {
          "assists": 1,
          "blocks": 0,
          "field_goals_attempted": 3,
          "field_goals_made": 1,
          "minutes": 10,
          "points": 2,
          "rebounds": 5,
          "starter": false,
          "steals": 0,
          "three_points_attempted": 2,
          "three_points_made": 0,
          "turnovers": 0
        },
        "9f2111cb-be0d-4569-af93-a4de5ab72a7e": {
          "assists": 1,
          "blocks": 0,
          "field_goals_attempted": 4,
          "field_goals_made": 2,
          "minutes": 4,
          "points": 6,
          "rebounds": 1,
          "starter": false,
          "steals": 0,
          "three_points_attempted": 1,
          "three_points_made": 0,
          "turnovers": 0
        },
        "b7022c10-2203-4b3e-877d-f539c32e0532": {
          "assists": 0,
          "blocks": 0,
          "field_goals_attempted": 5,
          "field_goals_made": 1,
          "minutes": 14,
          "points": 3,
          "rebounds": 0,
          "starter": false,
          "steals": 0,
          "three_points_attempted": 3,
          "three_points_made": 1,
          "turnovers": 1
        },
        "b725e63f-83b2-469d-8c34-41217a3a05d3": {
          "assists": 0,
          "blocks": 1,
          "field_goals_attempted": 14,
          "field_goals_made": 9,
          "minutes": 31,
          "points": 25,
          "rebounds": 6,
          "starter": true,
          "steals": 0,
          "three_points_attempted": 5,
          "three_points_made": 4,
          "turnovers": 1
        },
        "c040b6ef-2b8f-4338-ad6c-6a5973bb1484": {
          "assists": 0,
          "blocks": 0,
          "field_goals_attempted": 0,
          "field_goals_made": 0,
          "minutes": 0,
          "points": 0,
          "rebounds": 0,
          "starter": false,
          "steals": 0,
          "three_points_attempted": 0,
          "three_points_made": 0,
          "turnovers": 0
        },
        "d06c2a48-5fdc-40f8-9e7c-5b98d534aa4f": {
          "assists": 0,
          "blocks": 0,
          "field_goals_attempted": 2,
          "field_goals_made": 0,
          "minutes": 18,
          "points": 2,
          "rebounds": 0,
          "starter": false,
          "steals": 1,
          "three_points_attempted": 1,
          "three_points_made": 0,
          "turnovers": 1
        },
        "d25e2502-71da-4cf4-9068-63c09a55777b": {
          "assists": 4,
          "blocks": 1,
          "field_goals_attempted": 5,
          "field_goals_made": 4,
          "minutes": 30,
          "points": 9,
          "rebounds": 7,
          "starter": true,
          "steals": 2,
          "three_points_attempted": 0,
          "three_points_made": 0,
          "turnovers": 1
        },
        "d9935a9e-93fb-438e-956b-3600b9b87170": {
          "assists": 0,
          "blocks": 0,
          "field_goals_attempted": 0,
          "field_goals_made": 0,
          "minutes": 0,
          "points": 0,
          "rebounds": 0,
          "starter": false,
          "steals": 0,
          "three_points_attempted": 0,
          "three_points_made": 0,
          "turnovers": 0
        },
        "ddef089e-567a-4057-a913-5c93bbd0ec91": {
          "assists": 0,
          "blocks": 0,
          "field_goals_attempted": 2,
          "field_goals_made": 0,
          "minutes": 4,
          "points": 0,
          "rebounds": 0,
          "starter": false,
          "steals": 0,
          "three_points_attempted": 2,
          "three_points_made": 0,
          "turnovers": 1
        },
        "e9c185a4-48f9-497a-9da5-03d763ab11a3": {
          "assists": 5,
          "blocks": 3,
          "field_goals_attempted": 8,
          "field_goals_made": 7,
          "minutes": 36,
          "points": 18,
          "rebounds": 12,
          "starter": true,
          "steals": 1,
          "three_points_attempted": 0,
          "three_points_made": 0,
          "turnovers": 0
        },
        "f83d6641-0625-400e-a269-cd3e02d45813": {
          "assists": 1,
          "blocks": 0,
          "field_goals_attempted": 7,
          "field_goals_made": 1,
          "minutes": 17,
          "points": 2,
          "rebounds": 4,
          "starter": false,
          "steals": 0,
          "three_points_attempted": 2,
          "three_points_made": 0,
          "turnovers": 3
        },
        "f8ddd45a-b42c-4c8b-a0b0-08cf10ca3253": {
          "assists": 0,
          "blocks": 0,
          "field_goals_attempted": 0,
          "field_goals_made": 0,
          "minutes": 0,
          "points": 0,
          "rebounds": 0,
          "starter": false,
          "steals": 0,
          "three_points_attempted": 0,
          "three_points_made": 0,
          "turnovers": 0
        },
        "fb9a7f9e-8a0c-4e90-94e8-051dea709bef": {
          "assists": 3,
          "blocks": 1,
          "field_goals_attempted": 12,
          "field_goals_made": 7,
          "minutes": 37,
          "points": 16,
          "rebounds": 2,
          "starter": true,
          "steals": 0,
          "three_points_attempted": 3,
          "three_points_made": 2,
          "turnovers": 0
        }
      },
      "possession": "",
      "score_last_updated_ts": 1772767760,
      "series_stats": {
        "KXNBA3PT": "three_points_made",
        "KXNBAAST": "assists",
        "KXNBABLK": "blocks",
        "KXNBAPTS": "points",
        "KXNBAREB": "rebounds",
        "KXNBASTL": "steals"
      },
      "status": "closed",
      "widget_status": "finished",
      "winner": "583eca2f-fb46-11e1-82cb-f4ce4684ea4c"
    },
    "milestone_id": "1e3573ad-94a7-44b9-8c02-5a38e21ec103",
    "type": "basketball_game"
  }
}
