{
  "live_data": {
    "details": {
      "away_points": 122,
      "home_points": 114,
      "last_event_created_ts": 1772681266,
      "last_event_is_timeout": false,
      "last_play": "End of 4th Quarter.",
      "last_updated_ts": 1772682144,
      "period": 4,
      "period_remaining_time": "00:00",
      "period_type": "quarter",
      "player_stats": {
        "06d2662c-1e37-4b6c-8a1d-501a105e5644": {
          "assists": 0,
          "blocks": 0,
          "field_goals_attempted": 0,
          "field_goals_made": 0,
          "minutes": 0,
          "points": 0,
          "rebounds": 0,
          "starter": false,
          "steals": 0,
          "three_points_attempted": 0,
          "three_points_made": 0,
          "turnovers": 0
        },
        "0770fc2a-26b9-44c5-ab2c-26815ea7c6b0": {
          "assists": 4,
          "blocks": 0,
          "field_goals_attempted": 19,
          "field_goals_made": 11,
          "minutes": 37,
          "points": 30,
          "rebounds": 9,
          "starter": true,
          "steals": 1,
          "three_points_attempted": 8,
          "three_points_made": 3,
          "turnovers": 2
        },
        "0a2e3f0b-0b82-4806-aefc-e0130c226b14": {
          "assists": 1,
          "blocks": 0,
          "field_goals_attempted": 8,
          "field_goals_made": 5,
          "minutes": 22,
          "points": 13,
          "rebounds": 1,
          "starter": false,
          "steals": 1,
          "three_points_attempted": 4,
          "three_points_made": 3,
          "turnovers": 2
        },
        "0a9e0587-c565-41cc-93bd-74e1d1b1d375": {
          "assists": 0,
          "blocks": 0,
          "field_goals_attempted": 0,
          "field_goals_made": 0,
          "minutes": 0,
          "points": 0,
          "rebounds": 0,
          "starter": false,
          "steals": 0,
          "three_points_attempted": 0,
          "three_points_made": 0,
          "turnovers": 0
        },
        "0ff276a5-115b-4407-94b7-37e21c11454a": {
          "assists": 3,
          "blocks": 1,
          "field_goals_attempted": 12,
          "field_goals_made": 4,
          "minutes": 40,
          "points": 9,
          "rebounds": 7,
          "starter": true,
          "steals": 1,
          "three_points_attempted": 7,
          "three_points_made": 0,
          "turnovers": 1
        },
        "155ff771-bdf4-4a16-9908-6b555ff73ace": {
          "assists": 8,
          "blocks": 0,
          "field_goals_attempted": 7,
          "field_goals_made": 3,
          "minutes": 28,
          "points": 12,
          "rebounds": 2,
          "starter": false,
          "steals": 2,
          "three_points_attempted": 1,
          "three_points_made": 0,
          "turnovers": 3
        },
        "17380860-1ef9-4339-a500-e8bac0b0517c": {
          "assists": 0,
          "blocks": 0,
          "field_goals_attempted": 0,
          "field_goals_made": 0,
          "minutes": 0,
          "points": 0,
          "rebounds": 0,
          "starter": false,
          "steals": 0,
          "three_points_attempted": 0,
          "three_points_made": 0,
          "turnovers": 0
        },
        "3783ab8b-6b24-48d3-835e-3d18b2ebd848": {
          "assists": 0,
          "blocks": 0,
          "field_goals_attempted": 0,
          "field_goals_made": 0,
          "minutes": 0,
          "points": 0,
          "rebounds": 0,
          "starter": false,
          "steals": 0,
          "three_points_attempted": 0,
          "three_points_made": 0,
          "turnovers": 0
        },
        "3956631b-53dc-4cd9-8521-c8a113c806fa": {
          "assists": 0,
          "blocks": 0,
          "field_goals_attempted": 0,
          "field_goals_made": 0,
          "minutes": 0,
          "points": 0,
          "rebounds": 0,
          "starter": false,
          "steals": 0,
          "three_points_attempted": 0,
          "three_points_made": 0,
          "turnovers": 0
        },
        "41f8ada0-5160-4cff-b69e-a335d1a9eec7": {
          "assists": 1,
          "blocks": 0,
          "field_goals_attempted": 13,
          "field_goals_made": 5,
          "minutes": 34,
          "points": 17,
          "rebounds": 9,
          "starter": true,
          "steals": 2,
          "three_points_attempted": 5,
          "three_points_made": 2,
          "turnovers": 2
        },
        "49771603-2a9e-4029-b716-a0f32150dc14": {
          "assists": 0,
          "blocks": 0,
          "field_goals_attempted": 0,
          "field_goals_made": 0,
          "minutes": 0,
          "points": 0,
          "rebounds": 0,
          "starter": false,
          "steals": 0,
          "three_points_attempted": 0,
          "three_points_made": 0,
          "turnovers": 0
        },
        "4e4462ee-8564-4052-ba81-7c1e416c3e6f": {
          "assists": 0,
          "blocks": 0,
          "field_goals_attempted": 0,
          "field_goals_made": 0,
          "minutes": 0,
          "points": 0,
          "rebounds": 0,
          "starter": false,
          "steals": 0,
          "three_points_attempted": 0,
          "three_points_made": 0,
          "turnovers": 0
        },
        "53147479-51de-4a93-8beb-a70a78dc681f": {
          "assists": 0,
          "blocks": 0,
          "field_goals_attempted": 0,
          "field_goals_made": 0,
          "minutes": 0,
          "points": 0,
          "rebounds": 0,
          "starter": false,
          "steals": 0,
          "three_points_attempted": 0,
          "three_points_made": 0,
          "turnovers": 0
        },
        "58da1241-7818-4d04-9629-2a5a5795c5fa": {
          "assists": 0,
          "blocks": 0,
          "field_goals_attempted": 0,
          "field_goals_made": 0,
          "minutes": 0,
          "points": 0,
          "rebounds": 0,
          "starter": false,
          "steals": 0,
          "three_points_attempted": 0,
          "three_points_made": 0,
          "turnovers": 0
        },
        "5b48c281-6f74-4ed0-9252-17fcd483d5c9": {
          "assists": 7,
          "blocks": 2,
          "field_goals_attempted": 10,
          "field_goals_made": 4,
          "minutes": 29,
          "points": 12,
          "rebounds": 7,
          "starter": false,
          "steals": 0,
          "three_points_attempted": 5,
          "three_points_made": 2,
          "turnovers": 0
        },
        "5e85252f-a995-4dc2-8d1e-e7fd7503c803": {
          "assists": 5,
          "blocks": 1,
          "field_goals_attempted": 10,
          "field_goals_made": 4,
          "minutes": 33,
          "points": 11,
          "rebounds": 7,
          "starter": true,
          "steals": 2,
          "three_points_attempted": 4,
          "three_points_made": 1,
          "turnovers": 3
        },
        "751fd761-96ac-4859-aade-a38d1e2d5c4c": {
          "assists": 0,
          "blocks": 0,
          "field_goals_attempted": 0,
          "field_goals_made": 0,
          "minutes": 0,
          "points": 0,
          "rebounds": 0,
          "starter": false,
          "steals": 0,
          "three_points_attempted": 0,
          "three_points_made": 0,
          "turnovers": 0
        },
        "7ae937e9-691a-4645-9e65-29e0f5713858": {
          "assists": 2,
          "blocks": 0,
          "field_goals_attempted": 15,
          "field_goals_made": 8,
          "minutes": 32,
          "points": 24,
          "rebounds": 3,
          "starter": true,
          "steals": 2,
          "three_points_attempted": 8,
          "three_points_made": 4,
          "turnovers": 1
        },
        "80b360ed-9ea4-4cca-8ced-abba5c6a8471": {
          "assists": 1,
          "blocks": 4,
          "field_goals_attempted": 6,
          "field_goals_made": 3,
          "minutes": 13,
          "points": 7,
          "rebounds": 9,
          "starter": true,
          "steals": 1,
          "three_points_attempted": 1,
          "three_points_made": 0,
          "turnovers": 2
        },
        "8201e738-2f9d-43df-a356-adb225fc5dcb": {
          "assists": 2,
          "blocks": 0,
          "field_goals_attempted": 3,
          "field_goals_made": 2,
          "minutes": 16,
          "points": 6,
          "rebounds": 0,
          "starter": false,
          "steals": 1,
          "three_points_attempted": 2,
          "three_points_made": 2,
          "turnovers": 2
        },
        "8bcb0399-a016-42af-bbc8-b701f99abb96": {
          "assists": 0,
          "blocks": 0,
          "field_goals_attempted": 0,
          "field_goals_made": 0,
          "minutes": 0,
          "points": 0,
          "rebounds": 0,
          "starter": false,
          "steals": 0,
          "three_points_attempted": 0,
          "three_points_made": 0,
          "turnovers": 0
        },
        "9b1d114b-c1a7-455b-bb66-f6b74d7bec51": {
          "assists": 0,
          "blocks": 0,
          "field_goals_attempted": 6,
          "field_goals_made": 2,
          "minutes": 33,
          "points": 5,
          "rebounds": 5,
          "starter": true,
          "steals": 2,
          "three_points_attempted": 3,
          "three_points_made": 1,
          "turnovers": 1
        },
        "a867c548-86ed-4810-a289-a25576489f7f": {
          "assists": 0,
          "blocks": 0,
          "field_goals_attempted": 0,
          "field_goals_made": 0,
          "minutes": 0,
          "points": 0,
          "rebounds": 0,
          "starter": false,
          "steals": 0,
          "three_points_attempted": 0,
          "three_points_made": 0,
          "turnovers": 0
        },
        "aba92929-6fc0-476c-8462-35c5cf7a2cec": {
          "assists": 0,
          "blocks": 3,
          "field_goals_attempted": 12,
          "field_goals_made": 9,
          "minutes": 24,
          "points": 20,
          "rebounds": 11,
          "starter": false,
          "steals": 1,
          "three_points_attempted": 0,
          "three_points_made": 0,
          "turnovers": 2
        },
        "b75478af-67c3-4a19-9cee-b2930a77d78d": {
          "assists": 11,
          "blocks": 0,
          "field_goals_attempted": 19,
          "field_goals_made": 13,
          "minutes": 32,
          "points": 35,
          "rebounds": 5,
          "starter": true,
          "steals": 1,
          "three_points_attempted": 11,
          "three_points_made": 8,
          "turnovers": 3
        },
        "bea22e75-78de-4403-98b8-953d4a69aed4": {
          "assists": 0,
          "blocks": 0,
          "field_goals_attempted": 0,
          "field_goals_made": 0,
          "minutes": 0,
          "points": 0,
          "rebounds": 0,
          "starter": false,
          "steals": 0,
          "three_points_attempted": 0,
          "three_points_made": 0,
          "turnovers": 0
        },
        "c90b91a6-f684-4305-bf03-697ea7daf402": {
          "assists": 1,
          "blocks": 0,
          "field_goals_attempted": 3,
          "field_goals_made": 0,
          "minutes": 13,
          "points": 0,
          "rebounds": 3,
          "starter": false,
          "steals": 1,
          "three_points_attempted": 2,
          "three_points_made": 0,
          "turnovers": 1
        },
        "d651c84e-3e8c-48eb-befa-9bfb8b5a060c": {
          "assists": 0,
          "blocks": 0,
          "field_goals_attempted": 0,
          "field_goals_made": 0,
          "minutes": 0,
          "points": 0,
          "rebounds": 0,
          "starter": false,
          "steals": 0,
          "three_points_attempted": 0,
          "three_points_made": 0,
          "turnovers": 0
        },
        "d6d1d5a3-80ef-4687-af8c-dfaae4d6ea92": {
          "assists": 0,
          "blocks": 0,
          "field_goals_attempted": 0,
          "field_goals_made": 0,
          "minutes": 0,
          "points": 0,
          "rebounds": 0,
          "starter": false,
          "steals": 0,
          "three_points_attempted": 0,
          "three_points_made": 0,
          "turnovers": 0
        },
        "dab15c3b-1fd4-44ad-940c-55852685a6ae": {
          "assists": 3,
          "blocks": 0,
          "field_goals_attempted": 5,
          "field_goals_made": 1,
          "minutes": 22,
          "points": 3,
          "rebounds": 6,
          "starter": false,
          "steals": 1,
          "three_points_attempted": 4,
          "three_points_made": 1,
          "turnovers": 1
        },
        "f1bdc817-0c46-4f47-8007-e5701780c18f": {
          "assists": 1,
          "blocks": 3,
          "field_goals_attempted": 5,
          "field_goals_made": 2,
          "minutes": 23,
          "points": 4,
          "rebounds": 2,
          "starter": false,
          "steals": 1,
          "three_points_attempted": 2,
          "three_points_made": 0,
          "turnovers": 0
        },
        "f438ad3e-c75f-45b5-af2a-bf90dbf16fdd": {
          "assists": 1,
          "blocks": 3,
          "field_goals_attempted": 18,
          "field_goals_made": 8,
          "minutes": 34,
          "points": 20,
          "rebounds": 4,
          "starter": true,
          "steals": 1,
          "three_points_attempted": 2,
          "three_points_made": 1,
          "turnovers": 5
        },
        "f7a10ceb-9ddc-4afc-aea0-8c67b8b1dc6d": {
          "assists": 3,
          "blocks": 0,
          "field_goals_attempted": 11,
          "field_goals_made": 3,
          "minutes": 25,
          "points": 8,
          "rebounds": 1,
          "starter": true,
          "steals": 1,
          "three_points_attempted": 6,
          "three_points_made": 1,
          "turnovers": 2
        },
        "fc56c21a-a5a1-4ac3-aa90-1eb74d41da9f": {
          "assists": 0,
          "blocks": 0,
          "field_goals_attempted": 0,
          "field_goals_made": 0,
          "minutes": 0,
          "points": 0,
          "rebounds": 0,
          "starter": false,
          "steals": 0,
          "three_points_attempted": 0,
          "three_points_made": 0,
          "turnovers": 0
        },
        "fe5a04a5-0dc7-4373-baf9-36c4bced83a5": {
          "assists": 0,
          "blocks": 0,
          "field_goals_attempted": 0,
          "field_goals_made": 0,
          "minutes": 0,
          "points": 0,
          "rebounds": 0,
          "starter": false,
          "steals": 0,
          "three_points_attempted": 0,
          "three_points_made": 0,
          "turnovers": 0
        }
      },
      "possession": "",
      "score_last_updated_ts": 1772681250,
      "series_stats": {
        "KXNBA3PT": "three_points_made",
        "KXNBAAST": "assists",
        "KXNBABLK": "blocks",
        "KXNBAPTS": "points",
        "KXNBAREB": "rebounds",
        "KXNBASTL": "steals"
      },
      "status": "closed",
      "widget_status": "finished",
      "winner": "583ed056-fb46-11e1-82cb-f4ce4684ea4c"
    },
    "milestone_id": "bd3ec5ba-23d3-49a1-8b9c-93ac249aecf9",
    "type": "basketball_game"
  }
}
